[
  { "image": "1.jpg", "name": "Rose Bouquet", "price": 75 },
  { "image": "2.jpg", "name": "Tulip Bundle", "price": 60 },
  { "image": "3.jpg", "name": "Orchid Vase", "price": 90 },
  { "image": "4.jpg", "name": "Sunflower Pack", "price": 50 },
  { "image": "5.jpg", "name": "Lavender Set", "price": 120 },
  { "image": "6.jpg", "name": "Daisy Bunch", "price": 80 },
  { "image": "7.jpg", "name": "Peony Arrangement", "price": 55 },
  { "image": "8.jpg", "name": "Carnation Combo", "price": 70 },
  { "image": "9.jpg", "name": "Gardenia Display", "price": 95 },
  { "image": "10.jpg", "name": "Jasmine Pot", "price": 100 },
  { "image": "11.jpg", "name": "Lily Collection", "price": 65 },
  { "image": "12.jpg", "name": "Marigold Box", "price": 85 },
  { "image": "13.jpg", "name": "Azalea Jar", "price": 110 },
  { "image": "14.jpg", "name": "Begonia Assortment", "price": 60 },
  { "image": "15.jpg", "name": "Camellia Set", "price": 77 },
  { "image": "16.jpg", "name": "Chrysanthemum Mix", "price": 68 },
  { "image": "17.jpg", "name": "Daffodil Range", "price": 92 },
  { "image": "18.jpg", "name": "Freesia Group", "price": 73 },
  { "image": "19.jpg", "name": "Garden Rose", "price": 58 },
  { "image": "20.jpg", "name": "Hibiscus Pack", "price": 99 },
  { "image": "21.jpg", "name": "Iris Cluster", "price": 105 },
  { "image": "22.jpg", "name": "Jonquil Set", "price": 88 },
  { "image": "23.jpg", "name": "Lilac Bundle", "price": 79 },
  { "image": "24.jpg", "name": "Magnolia Box", "price": 115 },
  { "image": "25.jpg", "name": "Baby Hair Band 1", "price": 60 },
  { "image": "26.jpg", "name": "Baby Hair Band 2", "price": 60 },
  { "image": "27.jpg", "name": "Baby Hair Band 3", "price": 50 },
  { "image": "28.jpg", "name": "Invisibe chain ", "price": 50 }











  
]
